core/__init__.c
core/__init__.cpython-313-darwin.so
core/__init__.py
core/ai.c
core/ai.cpython-313-darwin.so
core/ai.py
core/cache_db.c
core/cache_db.cpython-313-darwin.so
core/cache_db.py
core/checker.c
core/checker.cpython-313-darwin.so
core/checker.py
core/cli.c
core/cli.cpython-313-darwin.so
core/cli.py
core/commands.c
core/commands.cpython-313-darwin.so
core/commands.py
core/completer.c
core/completer.cpython-313-darwin.so
core/completer.py
core/config.c
core/config.cpython-313-darwin.so
core/config.py
core/logger.c
core/logger.cpython-313-darwin.so
core/logger.py
core/shell.c
core/shell.cpython-313-darwin.so
core/shell.py
core/ui.c
core/ui.cpython-313-darwin.so
core/ui.py
core/utils.c
core/utils.cpython-313-darwin.so
core/utils.py
core/resources/fastapi_template.c
core/resources/fastapi_template.cpython-313-darwin.so
core/resources/fastapi_template.py
omga_cli-0.3.0.dist-info/licenses/LICENSE
omga_cli-0.3.0.dist-info/METADATA
omga_cli-0.3.0.dist-info/WHEEL
omga_cli-0.3.0.dist-info/entry_points.txt
omga_cli-0.3.0.dist-info/top_level.txt
omga_cli-0.3.0.dist-info/RECORD
