Metadata-Version: 2.4
Name: omga-cli
Version: 0.3.0
Summary: A CLI tool for code checking, explanation, and AI assistance
Author: Pouria Hosseini
Author-email: Pouria Hosseini <PouriaHosseini@outlook.com>
License: MIT
Keywords: cli,code-analysis,ai
Classifier: Programming Language :: Python :: 3
Classifier: License :: OSI Approved :: MIT License
Classifier: Operating System :: OS Independent
Requires-Python: >=3.10
License-File: LICENSE
Requires-Dist: prompt_toolkit>=3.0.0
Requires-Dist: click>=8.0.0
Requires-Dist: google-generativeai>=0.3.0
Requires-Dist: requests>=2.28.0
Requires-Dist: rich>=13.0.0
Requires-Dist: python-dotenv>=0.20.0
Dynamic: author
Dynamic: license-file
